biorepo/__init__.py
biorepo/biorepo.py
biorepo/env.py
biorepo/exception.py
biorepo/install.py
biorepo/repo.py
biorepo/shell.py
biorepo/source.py
biorepo/ui.py
biorepo/util.py
biorepo/cli/__init__.py
biorepo/cli/__main__.py
biorepo-0.1.3.dist-info/METADATA
biorepo-0.1.3.dist-info/WHEEL
biorepo-0.1.3.dist-info/entry_points.txt
biorepo-0.1.3.dist-info/top_level.txt
biorepo-0.1.3.dist-info/RECORD
